README.rst
setup.cfg
setup.py
onesignal/__init__.py
onesignal/onesignal_client.py
onesignal.egg-info/PKG-INFO
onesignal.egg-info/SOURCES.txt
onesignal.egg-info/dependency_links.txt
onesignal.egg-info/requires.txt
onesignal.egg-info/top_level.txt