Metadata-Version: 1.1
Name: onesignal
Version: 0.1
Summary: A Python wrapper for OneSignal API (http://onesignal.com)
Home-page: https://github.com/gettalent/one-signal-python-sdk
Author: Waqas Younas, Zohaib Ijaz, Ismael de Esteban
Author-email: waqas.younas@gmail.com, mzohaib.qc@gmail.com, ismael.deesteban@gmail.com
License: UNKNOWN
Keywords: onesignal,onesignalsdk
Platform: UNKNOWN
Classifier: Development Status :: 3 - Alpha
Classifier: Intended Audience :: Developers
Classifier: Topic :: Internet
Classifier: Topic :: Software Development :: Libraries
Classifier: Topic :: Software Development :: Libraries :: Python Modules
Classifier: Programming Language :: Python :: 2.7
